CHANGES.rst
DESCRIPTION.rst
MANIFEST.in
README.md
setup.py
src/fast_opex.egg-info/PKG-INFO
src/fast_opex.egg-info/SOURCES.txt
src/fast_opex.egg-info/dependency_links.txt
src/fast_opex.egg-info/top_level.txt
src/opex/_BBox.py
src/opex/_ObjectPrediction.py
src/opex/_ObjectPredictions.py
src/opex/_Polygon.py
src/opex/__init__.py
src/opex/_check_array_pair_polygon.py