Metadata-Version: 1.1
Name: fast-opex
Version: 0.0.2
Summary: Simpler and faster implementation of the OPEX JSON file format for object detection predictions.
Home-page: https://github.com/waikato-datamining/fast-opex
Author: Peter Reutemann
Author-email: fracpete@waikato.ac.nz
License: MIT License
Platform: UNKNOWN
Classifier: Development Status :: 4 - Beta
Classifier: License :: OSI Approved :: MIT License
Classifier: Topic :: Scientific/Engineering
Classifier: Programming Language :: Python :: 3
